{"is_source_file": true, "format": "JavaScript", "description": "This file defines a UI component named 'Button' using the LightningJS framework. It includes a template with dynamic content based on the component's state and a method to handle user input (pressing Enter) to toggle the favorited state.", "external_files": ["@lightningjs/blits"], "external_methods": ["Blits.Component"], "published": ["default"], "classes": [{"name": "Button", "description": "A LightningJS component representing a button with toggleable favorited state."}], "methods": [{"name": "input.enter", "description": "Handles the Enter key input to toggle the 'isFavorited' state."}], "calls": ["this.isFavorited = !this.isFavorited"], "search-terms": ["LightningJS Button component", "favorite toggle button", "LightningJS Component definition", "JS component with state and input handling"], "state": 2, "file_id": 4, "knowledge_revision": 76, "git_revision": "c5dec62abec345de20145e85c308cb38d25ed580", "ctags": [], "hash": "937bfe439a9c9f493682f4dc71047929", "format-version": 4, "code-base-name": "todo_list_frontend", "filename": "todo_list_frontend/src/components/Button.js", "revision_history": [{"76": "c5dec62abec345de20145e85c308cb38d25ed580"}]}